top.v
module smart_gate_controller (
    input clk_i,
    input reset_ni,
    input car_i,
    input pay_ok_i,
    input clear_i,
    input cnt_reset_i,
    output reg gate_open_o,
    output reg gate_close_o,
    output reg red_o,
    output reg yellow_o,
    output reg green_o,
    output reg [7:0] car_count_o
);

    localparam S0   = 3'd0;
    localparam S1   = 3'd1;
    localparam S2   = 3'd2;
    localparam S3   = 3'd3;
    localparam S4   = 3'd4;
    localparam S5   = 3'd5;
    localparam S6   = 3'd6;

    reg [2:0] state, next_state;
    reg [1:0] timer, next_timer;

    always @(posedge clk_i or negedge reset_ni) begin
        if (!reset_ni) begin
            state <= S0;
            timer <= 0;
            car_count_o <= 0;
        end else if (cnt_reset_i) begin
            car_count_o <= 0;
            state <= next_state;
            timer <= next_timer;
        end else begin
            state <= next_state;
            timer <= next_timer;
            if (state == S2 && car_count_o != 8'hFF) begin
                car_count_o <= car_count_o + 1;
            end
        end
    end

    always @(*) begin
        next_state = state;
        next_timer = 0;
        red_o = 0; yellow_o = 0; green_o = 0;
        gate_open_o = 0; gate_close_o = 0;

        case (state)
            S0: begin
                red_o = 1;
                if (car_i && pay_ok_i) next_state = S1;
            end

            S1: begin
                yellow_o = 1;
                if (timer < 1) begin
                    next_timer = timer + 1;
                    next_state = S1;
                end else begin
                    next_state = S2;
                end
            end

            S2: begin
                yellow_o = 1;
                if (clear_i) next_state = S3;
            end

            S3: begin
                green_o = 1;
                gate_open_o = 1;
                next_state = S4;
            end

            S4: begin
                green_o = 1;
                if (timer < 2) begin
                    next_timer = timer + 1;
                    next_state = S4;
                end else begin
                    next_state = S5;
                end
            end

            S5: begin
                yellow_o = 1;
                next_state = S6;
            end

            S6: begin
                red_o = 1;
                gate_close_o = 1;
                next_state = S0;
            end

            default: next_state = S0;
        endcase
    end
endmodule

tb.v
`timescale 1ns/1ps
// tb_smart_gate.v

module tb_smart_gate;

  // Clock/Reset
  reg clk_i;
  reg reset_ni;

  // Inputs
  reg car_i;
  reg pay_ok_i;
  reg clear_i;
  reg cnt_reset_i;

  // Outputs
  wire gate_open_o;
  wire gate_close_o;
  wire red_o;
  wire yellow_o;
  wire green_o;
  wire [7:0] car_count_o;

  // Test variables - moved to module level
  integer expected_count;
  integer i;
  integer lights;

  // DUT
  smart_gate_controller dut (
    .clk_i(clk_i),
    .reset_ni(reset_ni),
    .car_i(car_i),
    .pay_ok_i(pay_ok_i),
    .clear_i(clear_i),
    .cnt_reset_i(cnt_reset_i),
    .gate_open_o(gate_open_o),
    .gate_close_o(gate_close_o),
    .red_o(red_o),
    .yellow_o(yellow_o),
    .green_o(green_o),
    .car_count_o(car_count_o)
  );

  // Clock: 10ns period
  initial begin
    clk_i = 1'b0;
    forever #5 clk_i = ~clk_i;
  end

  // Generate waveform file
  initial begin
    $dumpfile("smart_gate.vcd");
    $dumpvars(0, tb_smart_gate);
  end

  // ----------------------
  // Helpers (Verilog tasks)
  // ----------------------
  task drive_request_one_cycle;
    begin
      @(negedge clk_i);
      car_i    = 1'b1;
      pay_ok_i = 1'b1;
      @(negedge clk_i);
      car_i    = 1'b0;
      pay_ok_i = 1'b0;
    end
  endtask

  task expect_lights;
    input r;
    input y;
    input g;
    input [8*32-1:0] tag; // fixed-size ASCII tag (Verilog-2001 trick)
    begin
      @(posedge clk_i);
      if (red_o !== r || yellow_o !== y || green_o !== g) begin
        $display("ERRORE luci (%0s): atteso R=%0d Y=%0d G=%0d ottenuto R=%0d Y=%0d G=%0d t=%0t",
                 tag, r,y,g, red_o,yellow_o,green_o, $time);
        $fatal;
      end
    end
  endtask

  task expect_motor_now;
    input open_pulse;
    input close_pulse;
    input [8*32-1:0] tag;
    begin
      if (gate_open_o !== open_pulse || gate_close_o !== close_pulse) begin
        $display("ERRORE motore (%0s): atteso open=%0d close=%0d ottenuto open=%0d close=%0d t=%0t",
                 tag, open_pulse, close_pulse, gate_open_o, gate_close_o, $time);
        $fatal;
      end
    end
  endtask

  // Invariants checked every cycle after reset release:
  // - exactly one light on
  // - motor commands mutually exclusive
  // - no open when clear_i is 0
  always @(posedge clk_i) begin
    if (reset_ni) begin
      lights = (red_o ? 1 : 0) + (yellow_o ? 1 : 0) + (green_o ? 1 : 0);
      if (lights != 1) begin
        $display("ERRORE invariante: luci non one-hot a t=%0t (R=%0d Y=%0d G=%0d)",
                 $time, red_o, yellow_o, green_o);
        $fatal;
      end
      if (gate_open_o && gate_close_o) begin
        $display("ERRORE invariante: open e close entrambi alti a t=%0t", $time);
        $fatal;
      end
      if (gate_open_o && !clear_i) begin
        $display("ERRORE invariante: gate_open_o alto mentre clear_i=0 a t=%0t", $time);
        $fatal;
      end
    end
  end

  // ----------------------
  // Main test sequence
  // ----------------------
  initial begin
    // init
    car_i = 0; pay_ok_i = 0; clear_i = 1; cnt_reset_i = 0;
    reset_ni = 0;

    // reset sequence
    repeat (3) @(posedge clk_i);
    reset_ni = 0;
    repeat (2) @(posedge clk_i);
    reset_ni = 1;

    // After reset -> IDLE (red), motors 0, count 0
    expect_lights(1,0,0, "after reset");
    expect_motor_now(0,0, "after reset");
    if (car_count_o !== 8'd0) begin
      $display("ERRORE conteggio dopo reset: ottenuto %0d", car_count_o);
      $fatal;
    end

    // ------------------------------------------------------------
    // TEST 1: basic sequence with clear_i = 1
    // ------------------------------------------------------------
    expected_count = 0;

    drive_request_one_cycle;

    // YELLOW_PRE for 2 cycles
    expect_lights(0,1,0, "T1 YELLOW_PRE 0"); expect_motor_now(0,0, "T1 YELLOW_PRE 0");
    expect_lights(0,1,0, "T1 YELLOW_PRE 1"); expect_motor_now(0,0, "T1 YELLOW_PRE 1");

    // WAIT_CLEAR (clear_i=1)
    expect_lights(0,1,0, "T1 WAIT_CLEAR");   expect_motor_now(0,0, "T1 WAIT_CLEAR");

    // OPEN (1 cycle): green + gate_open_o
    expect_lights(0,0,1, "T1 OPEN");   expect_motor_now(1,0, "T1 OPEN");
    expected_count = expected_count + 1;

    // GREEN 3 cycles
    expect_lights(0,0,1, "T1 GREEN 0");   expect_motor_now(0,0, "T1 GREEN 0");
    expect_lights(0,0,1, "T1 GREEN 1");   expect_motor_now(0,0, "T1 GREEN 1");
    expect_lights(0,0,1, "T1 GREEN 2");   expect_motor_now(0,0, "T1 GREEN 2");

    // YELLOW 1 cycle
    expect_lights(0,1,0, "T1 YELLOW");  expect_motor_now(0,0, "T1 YELLOW");

    // CLOSE 1 cycle
    expect_lights(1,0,0, "T1 CLOSE");  expect_motor_now(0,1, "T1 CLOSE");

    // Back to IDLE next cycle
    expect_lights(1,0,0, "T1 IDLE");   expect_motor_now(0,0, "T1 IDLE");

    if (car_count_o !== expected_count[7:0]) begin
      $display("ERRORE conteggio dopo T1: atteso %0d ottenuto %0d", expected_count, car_count_o);
      $fatal;
    end
    $display("TEST 1 SUPERATO");

    // ------------------------------------------------------------
    // TEST 2: clear_i holds low in WAIT_CLEAR; must not open until clear_i=1
    // ------------------------------------------------------------
    clear_i = 1'b1;
    drive_request_one_cycle;

    // YELLOW_PRE 2 cycles
    expect_lights(0,1,0, "T2 YELLOW_PRE 0"); expect_motor_now(0,0, "T2 YELLOW_PRE 0");
    expect_lights(0,1,0, "T2 YELLOW_PRE 1"); expect_motor_now(0,0, "T2 YELLOW_PRE 1");

    // Enter WAIT_CLEAR then force clear_i low for several cycles
    clear_i = 1'b0;
    expect_lights(0,1,0, "T2 WAIT_CLEAR 0"); expect_motor_now(0,0, "T2 WAIT_CLEAR 0");

    repeat (4) begin
      @(posedge clk_i);
      if (yellow_o !== 1'b1 || gate_open_o !== 1'b0) begin
        $display("ERRORE T2 hold: atteso giallo e non aperto mentre clear_i=0 a t=%0t", $time);
        $fatal;
      end
    end

    // Release clear_i
    @(negedge clk_i);
    clear_i = 1'b1;

    // still WAIT_CLEAR (yellow) on next posedge, then OPEN
    expect_lights(0,1,0, "T2 WAIT_CLEAR rel"); expect_motor_now(0,0, "T2 WAIT_CLEAR rel");
    expect_lights(0,0,1, "T2 OPEN");     expect_motor_now(1,0, "T2 OPEN");
    expected_count = expected_count + 1;

    // Finish sequence
    expect_lights(0,0,1, "T2 GREEN 0"); expect_motor_now(0,0, "T2 GREEN 0");
    expect_lights(0,0,1, "T2 GREEN 1"); expect_motor_now(0,0, "T2 GREEN 1");
    expect_lights(0,0,1, "T2 GREEN 2"); expect_motor_now(0,0, "T2 GREEN 2");
    expect_lights(0,1,0, "T2 YELLOW"); expect_motor_now(0,0, "T2 YELLOW");
    expect_lights(1,0,0, "T2 CLOSE"); expect_motor_now(0,1, "T2 CLOSE");
    expect_lights(1,0,0, "T2 IDLE");  expect_motor_now(0,0, "T2 IDLE");

    if (car_count_o !== expected_count[7:0]) begin
      $display("ERRORE conteggio dopo T2: atteso %0d ottenuto %0d", expected_count, car_count_o);
      $fatal;
    end
    $display("TEST 2 SUPERATO");

    // ------------------------------------------------------------
    // TEST 3: Counter Tests (Reset & Saturation)
    // ------------------------------------------------------------
    
    // Part A: Counter Reset during operation
    drive_request_one_cycle;

    // up to OPEN
    expect_lights(0,1,0, "T3A YELLOW_PRE 0"); expect_motor_now(0,0, "T3A YELLOW_PRE 0");
    expect_lights(0,1,0, "T3A YELLOW_PRE 1"); expect_motor_now(0,0, "T3A YELLOW_PRE 1");
    expect_lights(0,1,0, "T3A WAIT_CLEAR");   expect_motor_now(0,0, "T3A WAIT_CLEAR");
    expect_lights(0,0,1, "T3A OPEN");   expect_motor_now(1,0, "T3A OPEN");
    // Counter incremented here

    // GREEN 0
    expect_lights(0,0,1, "T3A GREEN 0");   expect_motor_now(0,0, "T3A GREEN 0");

    // Assert cnt_reset_i for 1 cycle during GREEN 1
    @(negedge clk_i);
    cnt_reset_i = 1'b1;
    @(posedge clk_i);
    if (green_o !== 1'b1 || gate_open_o !== 1'b0 || gate_close_o !== 1'b0) begin
      $display("ERRORE T3A: FSM disturbata da cnt_reset_i a t=%0t", $time);
      $fatal;
    end
    @(negedge clk_i);
    if (car_count_o !== 8'd0) begin
      $display("ERRORE T3A: contatore non resettato a 0, ottenuto %0d", car_count_o);
      $fatal;
    end
    cnt_reset_i = 1'b0;

    // remaining cycles and finish
    expect_lights(0,0,1, "T3A GREEN 2");   expect_motor_now(0,0, "T3A GREEN 2");
    expect_lights(0,1,0, "T3A YELLOW");  expect_motor_now(0,0, "T3A YELLOW");
    expect_lights(1,0,0, "T3A CLOSE");  expect_motor_now(0,1, "T3A CLOSE");
    expect_lights(1,0,0, "T3A IDLE");   expect_motor_now(0,0, "T3A IDLE");


    // Part B: Saturation to 255
    clear_i = 1'b1;
    // We loop enough times to overflow 8 bits if it wasn't saturating
    for (i = 0; i < 260; i = i + 1) begin
      drive_request_one_cycle;

      // Check key states just to be safe, but use abbreviated checks
      expect_lights(0,1,0, "T3B YELLOW_PRE"); expect_motor_now(0,0, "T3B YELLOW_PRE"); // cycle 1
      @(posedge clk_i); // cycle 2
      expect_lights(0,1,0, "T3B WAIT_CLEAR");  expect_motor_now(0,0, "T3B WAIT_CLEAR");
      expect_lights(0,0,1, "T3B OPEN");  expect_motor_now(1,0, "T3B OPEN");
      expect_lights(0,0,1, "T3B GREEN");    expect_motor_now(0,0, "T3B GREEN");  // cycle 1
      repeat(2) @(posedge clk_i); // GREEN 2,3
      expect_lights(0,1,0, "T3B YELLOW"); expect_motor_now(0,0, "T3B YELLOW");
      expect_lights(1,0,0, "T3B CLOSE"); expect_motor_now(0,1, "T3B CLOSE");
      expect_lights(1,0,0, "T3B IDLE");  expect_motor_now(0,0, "T3B IDLE");
    end

    if (car_count_o !== 8'hFF) begin
      $display("ERRORE T3B (saturazione): atteso 255 ottenuto %0d", car_count_o);
      $fatal;
    end
    $display("TEST 3 SUPERATO");

    $display("TUTTI I TEST SUPERATI ✅  car_count_o=%0d", car_count_o);
    $finish;
  end

endmodule

smart_gate.vcd
$date
	Wed Jan 14 11:40:48 2026
$end
$version
	Icarus Verilog
$end
$timescale
	1ps
$end
$scope module tb_smart_gate $end
$var wire 1 ! yellow_o $end
$var wire 1 " red_o $end
$var wire 1 # green_o $end
$var wire 1 $ gate_open_o $end
$var wire 1 % gate_close_o $end
$var wire 8 & car_count_o [7:0] $end
$var reg 1 ' car_i $end
$var reg 1 ( clear_i $end
$var reg 1 ) clk_i $end
$var reg 1 * cnt_reset_i $end
$var reg 1 + pay_ok_i $end
$var reg 1 , reset_ni $end
$var integer 32 - expected_count [31:0] $end
$var integer 32 . i [31:0] $end
$var integer 32 / lights [31:0] $end
$scope module dut $end
$var wire 1 ' car_i $end
$var wire 1 ( clear_i $end
$var wire 1 ) clk_i $end
$var wire 1 * cnt_reset_i $end
$var wire 1 + pay_ok_i $end
$var wire 1 , reset_ni $end
$var reg 8 0 car_count_o [7:0] $end
$var reg 1 % gate_close_o $end
$var reg 1 $ gate_open_o $end
$var reg 1 # green_o $end
$var reg 3 1 next_state [2:0] $end
$var reg 2 2 next_timer [1:0] $end
$var reg 1 " red_o $end
$var reg 3 3 state [2:0] $end
$var reg 2 4 timer [1:0] $end
$var reg 1 ! yellow_o $end
$upscope $end
$scope task drive_request_one_cycle $end
$upscope $end
$scope task expect_lights $end
$var reg 1 5 g $end
$var reg 1 6 r $end
$var reg 256 7 tag [255:0] $end
$var reg 1 8 y $end
$upscope $end
$scope task expect_motor_now $end
$var reg 1 9 close_pulse $end
$var reg 1 : open_pulse $end
$var reg 256 ; tag [255:0] $end
$upscope $end
$upscope $end
$enddefinitions $end
#0
$dumpvars
bx ;
x:
x9
x8
bx 7
x6
x5
b0 4
b0 3
b0 2
b0 1
b0 0
bx /
bx .
bx -
0,
0+
0*
0)
1(
0'
b0 &
0%
0$
0#
1"
0!
$end
#5000
1)
#10000
0)
#15000
1)
#20000
0)
#25000
1)
#30000
0)
#35000
1)
#40000
0)
#45000
b1 /
b110000101100110011101000110010101110010001000000111001001100101011100110110010101110100 7
05
08
16
1,
1)
#50000
0)
#55000
b0 -
b110000101100110011101000110010101110010001000000111001001100101011100110110010101110100 ;
09
0:
1)
#60000
b1 1
1"
1+
1'
0)
#65000
b1 2
1!
0"
b1 3
1)
#70000
1!
b1 2
b10101000011000100100000010110010100010101001100010011000100111101010111010111110101000001010010010001010010000000110000 7
18
06
0+
0'
0)
#75000
b10 1
1!
b0 2
b1 4
b10101000011000100100000010110010100010101001100010011000100111101010111010111110101000001010010010001010010000000110001 7
b10101000011000100100000010110010100010101001100010011000100111101010111010111110101000001010010010001010010000000110000 ;
1)
#80000
0)
#85000
b11 1
1!
b0 4
b10 3
b1010100001100010010000001010111010000010100100101010100010111110100001101001100010001010100000101010010 7
b10101000011000100100000010110010100010101001100010011000100111101010111010111110101000001010010010001010010000000110001 ;
1)
#90000
0)
#95000
b100 1
1$
1#
0!
b1 &
b1 0
b11 3
b1010100001100010010000001001111010100000100010101001110 7
15
08
b1010100001100010010000001010111010000010100100101010100010111110100001101001100010001010100000101010010 ;
1)
#100000
0)
#105000
b1 2
0$
1#
b100 3
b1010100001100010010000001000111010100100100010101000101010011100010000000110000 7
b1 -
b1010100001100010010000001001111010100000100010101001110 ;
1:
1)
#110000
0)
#115000
1#
b10 2
b1 4
b1010100001100010010000001000111010100100100010101000101010011100010000000110001 7
b1010100001100010010000001000111010100100100010101000101010011100010000000110000 ;
0:
1)
#120000
0)
#125000
b101 1
1#
b0 2
b10 4
b1010100001100010010000001000111010100100100010101000101010011100010000000110010 7
b1010100001100010010000001000111010100100100010101000101010011100010000000110001 ;
1)
#130000
0)
#135000
b110 1
1!
0#
b0 4
b101 3
b10101000011000100100000010110010100010101001100010011000100111101010111 7
05
18
b1010100001100010010000001000111010100100100010101000101010011100010000000110010 ;
1)
#140000
0)
#145000
b0 1
1%
1"
0!
b110 3
b101010000110001001000000100001101001100010011110101001101000101 7
08
16
b10101000011000100100000010110010100010101001100010011000100111101010111 ;
1)
#150000
0)
#155000
0%
1"
b0 3
b1010100001100010010000001001001010001000100110001000101 7
b101010000110001001000000100001101001100010011110101001101000101 ;
19
1)
#160000
0)
#165000
b1010100001100010010000001001001010001000100110001000101 ;
09
1)
#170000
b1 1
1"
1+
1'
0)
#175000
b1 2
1!
0"
b1 3
1)
#180000
1!
b1 2
b10101000011001000100000010110010100010101001100010011000100111101010111010111110101000001010010010001010010000000110000 7
18
06
0+
0'
0)
#185000
b10 1
1!
b0 2
b1 4
b10101000011001000100000010110010100010101001100010011000100111101010111010111110101000001010010010001010010000000110001 7
b10101000011001000100000010110010100010101001100010011000100111101010111010111110101000001010010010001010010000000110000 ;
1)
#190000
0)
#195000
b0 4
b10 3
1!
b10 1
b10101000011001000100000010101110100000101001001010101000101111101000011010011000100010101000001010100100010000000110000 7
0(
b10101000011001000100000010110010100010101001100010011000100111101010111010111110101000001010010010001010010000000110001 ;
1)
#200000
0)
#205000
b10 &
b10 0
b10101000011001000100000010101110100000101001001010101000101111101000011010011000100010101000001010100100010000000110000 ;
1)
#210000
0)
#215000
b11 &
b11 0
1)
#220000
0)
#225000
b100 &
b100 0
1)
#230000
0)
#235000
b101 &
b101 0
1)
#240000
0)
#245000
b110 &
b110 0
1)
#250000
b11 1
1!
b101010000110010001000000101011101000001010010010101010001011111010000110100110001000101010000010101001000100000011100100110010101101100 7
1(
0)
#255000
b100 1
1$
1#
0!
b111 &
b111 0
b11 3
b1010100001100100010000001001111010100000100010101001110 7
15
08
b101010000110010001000000101011101000001010010010101010001011111010000110100110001000101010000010101001000100000011100100110010101101100 ;
1)
#260000
0)
#265000
b1 2
0$
1#
b100 3
b1010100001100100010000001000111010100100100010101000101010011100010000000110000 7
b10 -
b1010100001100100010000001001111010100000100010101001110 ;
1:
1)
#270000
0)
#275000
1#
b10 2
b1 4
b1010100001100100010000001000111010100100100010101000101010011100010000000110001 7
b1010100001100100010000001000111010100100100010101000101010011100010000000110000 ;
0:
1)
#280000
0)
#285000
b101 1
1#
b0 2
b10 4
b1010100001100100010000001000111010100100100010101000101010011100010000000110010 7
b1010100001100100010000001000111010100100100010101000101010011100010000000110001 ;
1)
#290000
0)
#295000
b110 1
1!
0#
b0 4
b101 3
b10101000011001000100000010110010100010101001100010011000100111101010111 7
05
18
b1010100001100100010000001000111010100100100010101000101010011100010000000110010 ;
1)
#300000
0)
#305000
b0 1
1%
1"
0!
b110 3
b101010000110010001000000100001101001100010011110101001101000101 7
08
16
b10101000011001000100000010110010100010101001100010011000100111101010111 ;
1)
#310000
0)
#315000
0%
1"
b0 3
b1010100001100100010000001001001010001000100110001000101 7
b101010000110010001000000100001101001100010011110101001101000101 ;
19
1)
#320000
0)
#325000
b1010100001100100010000001001001010001000100110001000101 ;
09
1)
